actinia_rest_lib/__init__.py
actinia_rest_lib/deprecated_locations.py
actinia_rest_lib/endpoint_config.py
actinia_rest_lib/resource_base.py
actinia_rest_lib-1.0.0.dist-info/licenses/LICENSE.txt
actinia_rest_lib-1.0.0.dist-info/METADATA
actinia_rest_lib-1.0.0.dist-info/WHEEL
actinia_rest_lib-1.0.0.dist-info/top_level.txt
actinia_rest_lib-1.0.0.dist-info/RECORD
