Metadata-Version: 2.4
Name: actinia-rest-lib
Version: 1.0.0
Summary: An actinia library for common REST functionality
Author: Carmen Tawalika, Anika Weinmann, Lina Krisztian
Project-URL: Homepage, https://github.com/mundialis/actinia-rest-lib
Project-URL: Tutorial, https://mundialis.github.io/actinia_core
Project-URL: API_Docs, https://redocly.github.io/redoc/?url=https://actinia.mundialis.de/latest/swagger.json
Keywords: processing,earth observation,cloud-based processing,rest api,gis,grass gis,osgeo,example
Classifier: License :: OSI Approved :: Apache Software License
Classifier: Programming Language :: Python :: 3
Requires-Python: >=3.8
License-File: LICENSE.txt
Requires-Dist: flask
Requires-Dist: flask_restful_swagger_2
Requires-Dist: actinia-core
Provides-Extra: test
Requires-Dist: pytest; extra == "test"
Requires-Dist: pytest-cov; extra == "test"
Dynamic: license-file
